recheck/__init__.py
recheck/cli.py
recheck/requirements.py
recheck/textui.py
recheck-0.2.2.dist-info/DESCRIPTION.rst
recheck-0.2.2.dist-info/METADATA
recheck-0.2.2.dist-info/RECORD
recheck-0.2.2.dist-info/WHEEL
recheck-0.2.2.dist-info/entry_points.txt
recheck-0.2.2.dist-info/metadata.json
recheck-0.2.2.dist-info/top_level.txt
tests/__init__.py
tests/test_requirements.py
