Metadata-Version: 2.0
Name: recheck
Version: 0.2.2
Summary: Re(quirements)Check
Home-page: https://github.com/kevinjqiu/recheck
Author: Kevin J. Qiu
Author-email: kevin.qiu@points.com
License: UNKNOWN
Platform: UNKNOWN
Classifier: Development Status :: 2 - Pre-Alpha
Classifier: Programming Language :: Python
Classifier: Programming Language :: Python :: 2
Classifier: Programming Language :: Python :: 2.7
Requires-Dist: click (>=6.2)
